easyIoCtl
