Metadata-Version: 1.1
Name: easyIoCtl
Version: 1.2.3
Summary: Abstractions away from boring IO operations
Home-page: https://github.com/AustinGlover/EasyIoCtl
Author: Austin Glover
Author-email: dev_genuis@sphyreye.com
License: UNKNOWN
Download-URL: https://github.com/AustinGlover/EasyIoCtlarchive/1.0.tar.gz
Keywords: testing,logging,memory
Platform: UNKNOWN
